requests_retry.py
requests_retry-0.8.0.dist-info/DESCRIPTION.rst
requests_retry-0.8.0.dist-info/METADATA
requests_retry-0.8.0.dist-info/RECORD
requests_retry-0.8.0.dist-info/WHEEL
requests_retry-0.8.0.dist-info/metadata.json
requests_retry-0.8.0.dist-info/top_level.txt
